textual_inversion/__init__.py
textual_inversion/common/__init__.py
textual_inversion/common/testing/__init__.py
textual_inversion/integrations/__init__.py
textual_inversion/integrations/torch/__init__.py
textual_inversion/integrations/torch/data_collator.py
textual_inversion/integrations/torch/optim.py
textual_inversion/integrations/torch/textual_inversion_engine.py
textual_inversion/models/__init__.py
textual_inversion/models/stable_diffusion.py
textual_inversion/steps/__init__.py
textual_inversion/steps/create_pipeline.py
textual_inversion/steps/generate_images.py
textual_inversion/steps/setup_tokenizer_step.py
textual_inversion/steps/transform_data.py
textual_inversion/templates.py
textual_inversion/transforms/__init__.py
textual_inversion/transforms/examples.py
textual_inversion/transforms/image.py
textual_inversion/transforms/prompt.py
tango_textual_inversion-0.0.1.dist-info/METADATA
tango_textual_inversion-0.0.1.dist-info/WHEEL
tango_textual_inversion-0.0.1.dist-info/RECORD
